pydllmanager/__init__.py
PyDLLManager-1.2.0.dist-info/LICENCE
PyDLLManager-1.2.0.dist-info/METADATA
PyDLLManager-1.2.0.dist-info/WHEEL
PyDLLManager-1.2.0.dist-info/top_level.txt
PyDLLManager-1.2.0.dist-info/RECORD
