Metadata-Version: 2.2
Name: PyDLLManager
Version: 1.2.0
Summary: A library for effortlessly loading DLL files in Python.
Home-page: https://github.com/oar06g/PyDLLManager
Author: Omar Mohamed
Author-email: oar06g@gmail.com
Classifier: Programming Language :: Python :: 3
Classifier: License :: OSI Approved :: MIT License
Classifier: Operating System :: OS Independent
Requires-Python: >=3.6
License-File: LICENCE
Dynamic: author
Dynamic: author-email
Dynamic: classifier
Dynamic: description
Dynamic: description-content-type
Dynamic: home-page
Dynamic: requires-python
Dynamic: summary
